oneNeuron/__init__.py
oneNeuron/perceptron.py
oneNeuron_bandhavi47-0.0.1.dist-info/LICENSE
oneNeuron_bandhavi47-0.0.1.dist-info/METADATA
oneNeuron_bandhavi47-0.0.1.dist-info/WHEEL
oneNeuron_bandhavi47-0.0.1.dist-info/top_level.txt
oneNeuron_bandhavi47-0.0.1.dist-info/RECORD
