Metadata-Version: 2.1
Name: oneNeuron-bandhavi47
Version: 0.0.1
Summary: implementation of perceptron
Home-page: https://github.com/bandhavi47/oneNeuron
Author: bandhavi47
Author-email: 
License: UNKNOWN
Project-URL: Bug Tracker, https://github.com/bandhavi47/oneNeuron/issues
Platform: UNKNOWN
Classifier: Programming Language :: Python :: 3
Classifier: License :: OSI Approved :: MIT License
Classifier: Operating System :: OS Independent
Requires-Python: >=3.7
License-File: LICENSE
Requires-Dist: numpy
Requires-Dist: tqdm
